{
    "docs": [
        {
            "id": "21c55",
            "name": "Abracadavre - Treyarch",
            "description": "I started this months ago and havent finished it until now. Made 3 difficulties so more can enjoy. Also has little bit of Chroma in this one.  Hope you enjoy.",
            "uploader": {
                "id": 62252,
                "name": "Friction",
                "hash": "60254baf46eb150006d8b5ae",
                "avatar": "https://www.gravatar.com/avatar/60254baf46eb150006d8b5ae?d=retro",
                "type": "SIMPLE"
            },
            "metadata": {
                "bpm": 90.0,
                "duration": 366,
                "songName": "Abracadavre",
                "songSubName": "",
                "songAuthorName": "Treyarch",
                "levelAuthorName": "Friction"
            },
            "stats": {
                "plays": 0,
                "downloads": 0,
                "upvotes": 7,
                "downvotes": 2,
                "score": 0.6389
            },
            "uploaded": "2022-02-17T21:55:09.948469Z",
            "automapper": false,
            "ranked": false,
            "qualified": false,
            "versions": [
                {
                    "hash": "6ff8e284dd257ea6343600de4e8b0c43bd5e318b",
                    "state": "Published",
                    "createdAt": "2022-02-17T21:54:42.173628Z",
                    "diffs": [
                        {
                            "njs": 10.0,
                            "offset": 0.0,
                            "notes": 499,
                            "bombs": 28,
                            "obstacles": 70,
                            "nps": 1.396,
                            "length": 536.0,
                            "characteristic": "Standard",
                            "difficulty": "Hard",
                            "events": 1599,
                            "chroma": true,
                            "me": false,
                            "ne": false,
                            "cinema": false,
                            "seconds": 357.333,
                            "paritySummary": {
                                "errors": 0,
                                "warns": 0,
                                "resets": 2
                            }
                        },
                        {
                            "njs": 16.0,
                            "offset": 0.0,
                            "notes": 1149,
                            "bombs": 0,
                            "obstacles": 0,
                            "nps": 3.198,
                            "length": 539.0,
                            "characteristic": "Standard",
                            "difficulty": "Expert",
                            "events": 2713,
                            "chroma": false,
                            "me": false,
                            "ne": false,
                            "cinema": false,
                            "seconds": 359.333,
                            "paritySummary": {
                                "errors": 0,
                                "warns": 0,
                                "resets": 0
                            }
                        },
                        {
                            "njs": 16.0,
                            "offset": 0.0,
                            "notes": 1822,
                            "bombs": 0,
                            "obstacles": 3,
                            "nps": 5.054,
                            "length": 540.75,
                            "characteristic": "Standard",
                            "difficulty": "ExpertPlus",
                            "events": 3448,
                            "chroma": false,
                            "me": false,
                            "ne": false,
                            "cinema": false,
                            "seconds": 360.5,
                            "paritySummary": {
                                "errors": 1,
                                "warns": 0,
                                "resets": 0
                            }
                        }
                    ],
                    "downloadURL": "https://na.cdn.beatsaver.com/6ff8e284dd257ea6343600de4e8b0c43bd5e318b.zip",
                    "coverURL": "https://na.cdn.beatsaver.com/6ff8e284dd257ea6343600de4e8b0c43bd5e318b.jpg",
                    "previewURL": "https://na.cdn.beatsaver.com/6ff8e284dd257ea6343600de4e8b0c43bd5e318b.mp3"
                }
            ],
            "createdAt": "2022-02-16T14:48:37.632590Z",
            "updatedAt": "2022-02-17T21:55:09.948469Z",
            "lastPublishedAt": "2022-02-17T21:55:09.948469Z",
            "tags": [
                "metal",
                "video-game-soundtrack"
            ]
        },
        {
            "id": "216df",
            "name": "oh no our table is broken - Challenge Map",
            "description": "► Map Details:\n- Difficulty: Easy\n- Duration: 00:16\n- BPM: 112\n- Note Jump Speed: 12\n- Spawn Offset: 0\n- Total Notes: 148\n- Language: English\n\nIts a Meme-Challenge Map",
            "uploader": {
                "id": 4316113,
                "name": "RailyRoo",
                "avatar": "https://cdn.beatsaver.com/avatar/4316113.jpg",
                "type": "SIMPLE"
            },
            "metadata": {
                "bpm": 112.0,
                "duration": 16,
                "songName": "oh no our Table is Broken",
                "songSubName": "",
                "songAuthorName": "",
                "levelAuthorName": "RailyRoo"
            },
            "stats": {
                "plays": 0,
                "downloads": 0,
                "upvotes": 13,
                "downvotes": 0,
                "score": 0.7741
            },
            "uploaded": "2022-02-17T21:54:01.331428Z",
            "automapper": false,
            "ranked": false,
            "qualified": false,
            "versions": [
                {
                    "hash": "306290fa81beedf95c3fc1ad5cc6b7b31c7b5aa5",
                    "state": "Published",
                    "createdAt": "2022-02-09T12:38:07.073942Z",
                    "sageScore": 4,
                    "diffs": [
                        {
                            "njs": 12.0,
                            "offset": 0.0,
                            "notes": 148,
                            "bombs": 58,
                            "obstacles": 3,
                            "nps": 13.156,
                            "length": 21.0,
                            "characteristic": "Standard",
                            "difficulty": "Easy",
                            "events": 0,
                            "chroma": false,
                            "me": false,
                            "ne": false,
                            "cinema": false,
                            "seconds": 11.25,
                            "paritySummary": {
                                "errors": 10,
                                "warns": 0,
                                "resets": 1
                            }
                        }
                    ],
                    "downloadURL": "https://na.cdn.beatsaver.com/306290fa81beedf95c3fc1ad5cc6b7b31c7b5aa5.zip",
                    "coverURL": "https://na.cdn.beatsaver.com/306290fa81beedf95c3fc1ad5cc6b7b31c7b5aa5.jpg",
                    "previewURL": "https://na.cdn.beatsaver.com/306290fa81beedf95c3fc1ad5cc6b7b31c7b5aa5.mp3"
                }
            ],
            "createdAt": "2022-02-09T12:38:07.073942Z",
            "updatedAt": "2022-02-17T21:54:01.331428Z",
            "lastPublishedAt": "2022-02-17T21:54:01.331428Z",
            "tags": [
                "challenge",
                "speed",
                "tv-movie-soundtrack",
                "video-game-soundtrack"
            ]
        },
        {
            "id": "21db0",
            "name": "Washing Machine Heart ",
            "description": ":D",
            "uploader": {
                "id": 4323066,
                "name": "CloudVR.",
                "avatar": "https://www.gravatar.com/avatar/null?d=retro",
                "type": "SIMPLE"
            },
            "metadata": {
                "bpm": 106.0,
                "duration": 16,
                "songName": "Washing Machine Heart",
                "songSubName": "999",
                "songAuthorName": "CloudVR, BluuVR",
                "levelAuthorName": "Mistski"
            },
            "stats": {
                "plays": 0,
                "downloads": 0,
                "upvotes": 0,
                "downvotes": 3,
                "score": 0.3294
            },
            "uploaded": "2022-02-17T21:53:04.312277Z",
            "automapper": false,
            "ranked": false,
            "qualified": false,
            "versions": [
                {
                    "hash": "a864e27aa3e44fe561b863a33bf688b4f102952d",
                    "state": "Published",
                    "createdAt": "2022-02-17T21:52:30.557804Z",
                    "sageScore": 1,
                    "diffs": [
                        {
                            "njs": 18.0,
                            "offset": 0.0,
                            "notes": 71,
                            "bombs": 33,
                            "obstacles": 4,
                            "nps": 5.143,
                            "length": 24.391,
                            "characteristic": "Standard",
                            "difficulty": "ExpertPlus",
                            "events": 770,
                            "chroma": false,
                            "me": false,
                            "ne": false,
                            "cinema": false,
                            "seconds": 13.806,
                            "paritySummary": {
                                "errors": 17,
                                "warns": 4,
                                "resets": 3
                            }
                        }
                    ],
                    "downloadURL": "https://na.cdn.beatsaver.com/a864e27aa3e44fe561b863a33bf688b4f102952d.zip",
                    "coverURL": "https://na.cdn.beatsaver.com/a864e27aa3e44fe561b863a33bf688b4f102952d.jpg",
                    "previewURL": "https://na.cdn.beatsaver.com/a864e27aa3e44fe561b863a33bf688b4f102952d.mp3"
                }
            ],
            "createdAt": "2022-02-17T21:52:30.557804Z",
            "updatedAt": "2022-02-17T21:53:04.312277Z",
            "lastPublishedAt": "2022-02-17T21:53:04.312277Z"
        },
        {
            "id": "21da4",
            "name": "Silentroom - Nhelv",
            "description": "1... 2... 3... 4... TECH STREAMMMMMMMMMM\n\nEstimated Stars: 11.5-12.8⭐",
            "uploader": {
                "id": 4284595,
                "name": "oermergeesh",
                "hash": "5fcbd389607cfe000694a3cb",
                "avatar": "https://cdn.beatsaver.com/avatar/798005132964266045.png",
                "type": "DISCORD"
            },
            "metadata": {
                "bpm": 175.89,
                "duration": 413,
                "songName": "Nhelv",
                "songSubName": "",
                "songAuthorName": "Silentroom",
                "levelAuthorName": "oermergeesh"
            },
            "stats": {
                "plays": 0,
                "downloads": 0,
                "upvotes": 0,
                "downvotes": 0,
                "score": 0.5
            },
            "uploaded": "2022-02-17T21:24:00.068457Z",
            "automapper": false,
            "ranked": false,
            "qualified": false,
            "versions": [
                {
                    "hash": "30c8b341eea99033a7456669554a48f455747b45",
                    "state": "Published",
                    "createdAt": "2022-02-17T21:46:53.229824Z",
                    "sageScore": 3,
                    "diffs": [
                        {
                            "njs": 22.75,
                            "offset": -0.75,
                            "notes": 2832,
                            "bombs": 608,
                            "obstacles": 768,
                            "nps": 7.318,
                            "length": 1134.5,
                            "characteristic": "Standard",
                            "difficulty": "ExpertPlus",
                            "events": 10469,
                            "chroma": false,
                            "me": false,
                            "ne": false,
                            "cinema": false,
                            "seconds": 387.003,
                            "paritySummary": {
                                "errors": 1,
                                "warns": 171,
                                "resets": 17
                            }
                        }
                    ],
                    "downloadURL": "https://na.cdn.beatsaver.com/30c8b341eea99033a7456669554a48f455747b45.zip",
                    "coverURL": "https://na.cdn.beatsaver.com/30c8b341eea99033a7456669554a48f455747b45.jpg",
                    "previewURL": "https://na.cdn.beatsaver.com/30c8b341eea99033a7456669554a48f455747b45.mp3"
                }
            ],
            "createdAt": "2022-02-17T21:23:50.352041Z",
            "updatedAt": "2022-02-17T21:47:54.262890Z",
            "lastPublishedAt": "2022-02-17T21:47:03.544433Z",
            "tags": [
                "speed",
                "tech",
                "drum-and-bass",
                "electronic"
            ]
        },
        {
            "id": "21da7",
            "name": "Memme - Acid Burst ",
            "description": "Collab with Dan! Techy map and not too hard, just some arm and visual tech.\n\nBPM: 180\nStyle: Tech\n\n=============\nDifficulty Estimate: 6/10 | Lvl 5-7? (BSCC)",
            "uploader": {
                "id": 4284314,
                "name": "Smile249",
                "hash": "5cff0b7798cc5a672c856253",
                "avatar": "https://cdn.beatsaver.com/avatar/667800699693957120.png",
                "type": "SIMPLE"
            },
            "metadata": {
                "bpm": 180.0,
                "duration": 128,
                "songName": "Acid Burst",
                "songSubName": "",
                "songAuthorName": "Memme",
                "levelAuthorName": "Smile & Olfah"
            },
            "stats": {
                "plays": 0,
                "downloads": 0,
                "upvotes": 1,
                "downvotes": 0,
                "score": 0.5942
            },
            "uploaded": "2022-02-17T21:39:04.919496Z",
            "automapper": false,
            "ranked": false,
            "qualified": false,
            "versions": [
                {
                    "hash": "cceb58872c37ce9b429fdfaa331b655f5c5bc664",
                    "state": "Published",
                    "createdAt": "2022-02-17T21:38:08.628236Z",
                    "sageScore": 4,
                    "diffs": [
                        {
                            "njs": 22.0,
                            "offset": -0.72,
                            "notes": 1194,
                            "bombs": 11,
                            "obstacles": 23,
                            "nps": 9.734,
                            "length": 368.0,
                            "characteristic": "Standard",
                            "difficulty": "ExpertPlus",
                            "events": 1401,
                            "chroma": false,
                            "me": false,
                            "ne": false,
                            "cinema": false,
                            "seconds": 122.667,
                            "paritySummary": {
                                "errors": 0,
                                "warns": 2,
                                "resets": 3
                            }
                        }
                    ],
                    "downloadURL": "https://na.cdn.beatsaver.com/cceb58872c37ce9b429fdfaa331b655f5c5bc664.zip",
                    "coverURL": "https://na.cdn.beatsaver.com/cceb58872c37ce9b429fdfaa331b655f5c5bc664.jpg",
                    "previewURL": "https://na.cdn.beatsaver.com/cceb58872c37ce9b429fdfaa331b655f5c5bc664.mp3"
                }
            ],
            "createdAt": "2022-02-17T21:38:08.628236Z",
            "updatedAt": "2022-02-17T21:39:04.919496Z",
            "lastPublishedAt": "2022-02-17T21:39:04.919496Z",
            "tags": [
                "tech",
                "electronic",
                "challenge"
            ]
        },
        {
            "id": "21da6",
            "name": "Rahatt - Mariquita Breakcore",
            "description": "i hope you like walls",
            "uploader": {
                "id": 4285046,
                "name": "spookybeard",
                "hash": "5cff0b7698cc5a672c854a12",
                "avatar": "https://cdn.beatsaver.com/avatar/282250845221814272.png",
                "type": "DISCORD"
            },
            "metadata": {
                "bpm": 220.0,
                "duration": 173,
                "songName": "Mariquita Breakcore",
                "songSubName": "",
                "songAuthorName": "Rahatt",
                "levelAuthorName": "SpookyBeard"
            },
            "stats": {
                "plays": 0,
                "downloads": 0,
                "upvotes": 2,
                "downvotes": 1,
                "score": 0.5569
            },
            "uploaded": "2022-02-17T21:37:44.959167Z",
            "automapper": false,
            "ranked": false,
            "qualified": false,
            "versions": [
                {
                    "hash": "d6d714eec1b9083b28d1d15a51ca62b3c54be73b",
                    "state": "Published",
                    "createdAt": "2022-02-17T21:37:36.557915Z",
                    "sageScore": 6,
                    "diffs": [
                        {
                            "njs": 22.0,
                            "offset": -0.18909109,
                            "notes": 2471,
                            "bombs": 0,
                            "obstacles": 449,
                            "nps": 14.52,
                            "length": 624.0,
                            "characteristic": "Standard",
                            "difficulty": "ExpertPlus",
                            "events": 0,
                            "chroma": false,
                            "me": false,
                            "ne": false,
                            "cinema": false,
                            "seconds": 170.182,
                            "paritySummary": {
                                "errors": 5,
                                "warns": 30,
                                "resets": 0
                            }
                        }
                    ],
                    "downloadURL": "https://na.cdn.beatsaver.com/d6d714eec1b9083b28d1d15a51ca62b3c54be73b.zip",
                    "coverURL": "https://na.cdn.beatsaver.com/d6d714eec1b9083b28d1d15a51ca62b3c54be73b.jpg",
                    "previewURL": "https://na.cdn.beatsaver.com/d6d714eec1b9083b28d1d15a51ca62b3c54be73b.mp3"
                }
            ],
            "createdAt": "2022-02-17T21:37:36.557915Z",
            "updatedAt": "2022-02-17T21:37:44.959167Z",
            "lastPublishedAt": "2022-02-17T21:37:44.959167Z"
        },
        {
            "id": "21da5",
            "name": "ICDD - Danzai No Honoo To Koibito-Tachi No Rondo",
            "description": "Imperial Circus Dead Decadence <3\r\namazing band, love their music.\r\n\r\ngl meow",
            "uploader": {
                "id": 4290101,
                "name": "Yasu",
                "avatar": "https://cdn.beatsaver.com/avatar/311141957743280129.png",
                "type": "DISCORD"
            },
            "metadata": {
                "bpm": 174.0,
                "duration": 251,
                "songName": "Danzai No Honoo To Koibito-Tachi No Rondo",
                "songSubName": "",
                "songAuthorName": "Imperial Circus Dead Decadence",
                "levelAuthorName": "Yasu"
            },
            "stats": {
                "plays": 0,
                "downloads": 0,
                "upvotes": 5,
                "downvotes": 1,
                "score": 0.6478
            },
            "uploaded": "2022-02-17T21:26:38.344637Z",
            "automapper": false,
            "ranked": false,
            "qualified": false,
            "versions": [
                {
                    "hash": "712437e2a1fbb4014f613599c9ee3435ad523285",
                    "state": "Published",
                    "createdAt": "2022-02-17T21:26:33.207628Z",
                    "sageScore": 6,
                    "diffs": [
                        {
                            "njs": 22.0,
                            "offset": -0.5,
                            "notes": 2136,
                            "bombs": 22,
                            "obstacles": 74,
                            "nps": 8.749,
                            "length": 708.0,
                            "characteristic": "Standard",
                            "difficulty": "ExpertPlus",
                            "events": 7600,
                            "chroma": false,
                            "me": false,
                            "ne": false,
                            "cinema": false,
                            "seconds": 244.138,
                            "paritySummary": {
                                "errors": 0,
                                "warns": 0,
                                "resets": 2
                            }
                        }
                    ],
                    "downloadURL": "https://na.cdn.beatsaver.com/712437e2a1fbb4014f613599c9ee3435ad523285.zip",
                    "coverURL": "https://na.cdn.beatsaver.com/712437e2a1fbb4014f613599c9ee3435ad523285.jpg",
                    "previewURL": "https://na.cdn.beatsaver.com/712437e2a1fbb4014f613599c9ee3435ad523285.mp3"
                }
            ],
            "createdAt": "2022-02-17T21:26:33.207628Z",
            "updatedAt": "2022-02-17T21:26:38.344637Z",
            "lastPublishedAt": "2022-02-17T21:26:38.344637Z"
        },
        {
            "id": "1b4b6",
            "name": "Smokey Joe & The Kid - Lonesome Blues",
            "description": "The boys are back, and I am glad that map is fun to play! Way better patterns and playability than the ranked one. I will try to make it rankable, but we will see how will it go.\n\nDiscord - Artjoms#2000",
            "uploader": {
                "id": 4284607,
                "name": "artjoms",
                "hash": "5dab6e672319ea00060667ab",
                "avatar": "https://cdn.beatsaver.com/avatar/203250289023778816.png",
                "type": "DISCORD"
            },
            "metadata": {
                "bpm": 190.0,
                "duration": 246,
                "songName": "Lonesome Blues",
                "songSubName": "",
                "songAuthorName": "Smokey Joe & The Kid",
                "levelAuthorName": "Artjoms"
            },
            "stats": {
                "plays": 0,
                "downloads": 0,
                "upvotes": 16,
                "downvotes": 0,
                "score": 0.7869
            },
            "uploaded": "2021-08-15T12:29:25.641871Z",
            "automapper": false,
            "ranked": false,
            "qualified": false,
            "versions": [
                {
                    "hash": "a529a4bfd9b374b625589413cdec5ef2d998782e",
                    "state": "Published",
                    "createdAt": "2021-08-15T12:29:05.109810Z",
                    "sageScore": 4,
                    "diffs": [
                        {
                            "njs": 20.0,
                            "offset": -0.417,
                            "notes": 918,
                            "bombs": 6,
                            "obstacles": 451,
                            "nps": 4.326,
                            "length": 672.0,
                            "characteristic": "Standard",
                            "difficulty": "ExpertPlus",
                            "events": 3892,
                            "chroma": false,
                            "me": false,
                            "ne": false,
                            "cinema": false,
                            "seconds": 212.211,
                            "paritySummary": {
                                "errors": 0,
                                "warns": 0,
                                "resets": 0
                            }
                        }
                    ],
                    "downloadURL": "https://na.cdn.beatsaver.com/a529a4bfd9b374b625589413cdec5ef2d998782e.zip",
                    "coverURL": "https://na.cdn.beatsaver.com/a529a4bfd9b374b625589413cdec5ef2d998782e.jpg",
                    "previewURL": "https://na.cdn.beatsaver.com/a529a4bfd9b374b625589413cdec5ef2d998782e.mp3"
                }
            ],
            "createdAt": "2021-08-15T12:29:25.641871Z",
            "updatedAt": "2022-02-17T21:07:50.090944Z",
            "lastPublishedAt": "2021-08-15T12:29:25.641871Z",
            "tags": [
                "balanced",
                "drum-and-bass"
            ]
        },
        {
            "id": "1cc9d",
            "name": "Camellia - Xeroa (\"preconnaiXance\" Long ver.)",
            "description": "I will try for rank, so I will probably reupload a lot, because I want to make this into my best creation.\n\nthanks Davaay, Denyah and Anammelech for the mod/playtest.\nthanks Purp1e for the QAT mod.\n:)\n\n\n\nDM me for feedback: Spectre#7395",
            "uploader": {
                "id": 4285340,
                "name": "spectre158",
                "hash": "5e11bf7cba32cf00064caf8f",
                "avatar": "https://cdn.beatsaver.com/avatar/409788531318456331.png",
                "type": "DISCORD"
            },
            "metadata": {
                "bpm": 301.0,
                "duration": 291,
                "songName": "Xeroa",
                "songSubName": "(\"preconnaiXance\" Long ver.)",
                "songAuthorName": "Camellia",
                "levelAuthorName": "Spectre158"
            },
            "stats": {
                "plays": 0,
                "downloads": 0,
                "upvotes": 40,
                "downvotes": 4,
                "score": 0.779
            },
            "uploaded": "2021-10-03T20:10:42.263793Z",
            "automapper": false,
            "ranked": false,
            "qualified": false,
            "versions": [
                {
                    "hash": "f926f8fc92ad1c02134c3168faa137a2ca076fe6",
                    "state": "Published",
                    "createdAt": "2022-02-17T20:43:51.249272Z",
                    "sageScore": 4,
                    "diffs": [
                        {
                            "njs": 20.5,
                            "offset": -1.5,
                            "notes": 2196,
                            "bombs": 241,
                            "obstacles": 323,
                            "nps": 7.693,
                            "length": 1432.0,
                            "characteristic": "Standard",
                            "difficulty": "Expert",
                            "events": 10418,
                            "chroma": false,
                            "me": false,
                            "ne": false,
                            "cinema": false,
                            "seconds": 285.449,
                            "paritySummary": {
                                "errors": 0,
                                "warns": 0,
                                "resets": 14
                            }
                        },
                        {
                            "njs": 22.5,
                            "offset": -1.75,
                            "notes": 3312,
                            "bombs": 298,
                            "obstacles": 345,
                            "nps": 11.603,
                            "length": 1432.0,
                            "characteristic": "Standard",
                            "difficulty": "ExpertPlus",
                            "events": 10418,
                            "chroma": false,
                            "me": false,
                            "ne": false,
                            "cinema": false,
                            "seconds": 285.449,
                            "paritySummary": {
                                "errors": 0,
                                "warns": 0,
                                "resets": 17
                            }
                        }
                    ],
                    "downloadURL": "https://na.cdn.beatsaver.com/f926f8fc92ad1c02134c3168faa137a2ca076fe6.zip",
                    "coverURL": "https://na.cdn.beatsaver.com/f926f8fc92ad1c02134c3168faa137a2ca076fe6.jpg",
                    "previewURL": "https://na.cdn.beatsaver.com/f926f8fc92ad1c02134c3168faa137a2ca076fe6.mp3"
                }
            ],
            "createdAt": "2021-10-03T20:10:20.381156Z",
            "updatedAt": "2022-02-17T21:07:21.015545Z",
            "lastPublishedAt": "2022-02-17T20:43:56.142541Z",
            "tags": [
                "speed",
                "speedcore",
                "electronic"
            ]
        },
        {
            "id": "21d97",
            "name": "Goodbye Moonmen (spiral practice)",
            "description": "spiral practice\ndont play this if you dont know what spirals are\n\nex+ = 512bpm\nex = 384bpm",
            "uploader": {
                "id": 4292686,
                "name": "OtherPatrick",
                "avatar": "https://cdn.beatsaver.com/avatar/432556223527911434.png",
                "type": "DISCORD"
            },
            "metadata": {
                "bpm": 128.0,
                "duration": 60,
                "songName": "Goodbye Moonmen",
                "songSubName": "(Remix)",
                "songAuthorName": "The Living Tombstone",
                "levelAuthorName": "OtherPatrick"
            },
            "stats": {
                "plays": 0,
                "downloads": 0,
                "upvotes": 2,
                "downvotes": 6,
                "score": 0.379
            },
            "uploaded": "2022-02-17T20:44:32.118978Z",
            "automapper": false,
            "ranked": false,
            "qualified": false,
            "versions": [
                {
                    "hash": "acf7a52398bcb89d68b271de7a6b5a92f099fca4",
                    "state": "Published",
                    "createdAt": "2022-02-17T20:43:35.411249Z",
                    "diffs": [
                        {
                            "njs": 21.0,
                            "offset": 0.0,
                            "notes": 368,
                            "bombs": 0,
                            "obstacles": 0,
                            "nps": 13.733,
                            "length": 57.166,
                            "characteristic": "Standard",
                            "difficulty": "Expert",
                            "events": 0,
                            "chroma": false,
                            "me": false,
                            "ne": false,
                            "cinema": false,
                            "seconds": 26.797,
                            "paritySummary": {
                                "errors": 0,
                                "warns": 0,
                                "resets": 0
                            }
                        },
                        {
                            "njs": 21.0,
                            "offset": 0.0,
                            "notes": 496,
                            "bombs": 0,
                            "obstacles": 0,
                            "nps": 18.483,
                            "length": 57.25,
                            "characteristic": "Standard",
                            "difficulty": "ExpertPlus",
                            "events": 0,
                            "chroma": false,
                            "me": false,
                            "ne": false,
                            "cinema": false,
                            "seconds": 26.836,
                            "paritySummary": {
                                "errors": 472,
                                "warns": 0,
                                "resets": 0
                            }
                        }
                    ],
                    "downloadURL": "https://na.cdn.beatsaver.com/acf7a52398bcb89d68b271de7a6b5a92f099fca4.zip",
                    "coverURL": "https://na.cdn.beatsaver.com/acf7a52398bcb89d68b271de7a6b5a92f099fca4.jpg",
                    "previewURL": "https://na.cdn.beatsaver.com/acf7a52398bcb89d68b271de7a6b5a92f099fca4.mp3"
                }
            ],
            "createdAt": "2022-02-17T20:43:35.411249Z",
            "updatedAt": "2022-02-17T20:44:32.118978Z",
            "lastPublishedAt": "2022-02-17T20:44:32.118978Z",
            "tags": [
                "challenge"
            ]
        },
        {
            "id": "21d83",
            "name": "TJ_beastboy - FLiP iT/SKiP iT",
            "description": "Chroma map, dont mind the parity warnings just precision placement.",
            "uploader": {
                "id": 4284289,
                "name": "vadez",
                "hash": "607c93b2cd73ba00060b137f",
                "avatar": "https://cdn.beatsaver.com/avatar/530886659240230915.png",
                "type": "DISCORD"
            },
            "metadata": {
                "bpm": 160.0,
                "duration": 170,
                "songName": "FLiP iT/SKiP iT",
                "songSubName": "",
                "songAuthorName": "TJ_beastboy",
                "levelAuthorName": "Vadez"
            },
            "stats": {
                "plays": 0,
                "downloads": 0,
                "upvotes": 11,
                "downvotes": 1,
                "score": 0.7242
            },
            "uploaded": "2022-02-17T18:56:17.618819Z",
            "automapper": false,
            "ranked": false,
            "qualified": false,
            "versions": [
                {
                    "hash": "6741bb748034dd240899bd85056a13ff7a8e9b38",
                    "state": "Published",
                    "createdAt": "2022-02-17T19:09:12.289115Z",
                    "sageScore": 3,
                    "diffs": [
                        {
                            "njs": 20.0,
                            "offset": -0.3,
                            "notes": 817,
                            "bombs": 15,
                            "obstacles": 0,
                            "nps": 5.63,
                            "length": 387.0,
                            "characteristic": "Standard",
                            "difficulty": "ExpertPlus",
                            "events": 3430,
                            "chroma": true,
                            "me": false,
                            "ne": true,
                            "cinema": false,
                            "seconds": 145.125,
                            "paritySummary": {
                                "errors": 0,
                                "warns": 0,
                                "resets": 4
                            }
                        }
                    ],
                    "downloadURL": "https://na.cdn.beatsaver.com/6741bb748034dd240899bd85056a13ff7a8e9b38.zip",
                    "coverURL": "https://na.cdn.beatsaver.com/6741bb748034dd240899bd85056a13ff7a8e9b38.jpg",
                    "previewURL": "https://na.cdn.beatsaver.com/6741bb748034dd240899bd85056a13ff7a8e9b38.mp3"
                }
            ],
            "createdAt": "2022-02-17T18:55:52.481304Z",
            "updatedAt": "2022-02-17T20:41:36.700215Z",
            "lastPublishedAt": "2022-02-17T19:10:03.673172Z",
            "tags": [
                "hip-hop-rap"
            ]
        },
        {
            "id": "1f7d2",
            "name": "Eminem Ft. Dido - Stan",
            "description": "Chroma map, for the best expirience go to player options and make sure you have all the envoirmental effects set to \"All Effects\" also if u play with custom notes u wanna turn them off for this one or some features wont work. Also make sure to use the custom colours the song gives you so if you don't see gray and black in the beginning make sure to turn off override colours.\n\nSorry for the score reset but the were common complaints that had to be fixed, also the settings above should now automaticly be recommended.\n\nhere were the top 3 scores before the reset:\n\n1\tcrypticnugget\t1.713.564\t-\t97.21%\t0.00\n2\tZemphisTV\t1.701.657\t-\t96.53%\t0.00\n3\tStevenBTW\t1.688.490\t-\t95.78%\t0.00",
            "uploader": {
                "id": 4284289,
                "name": "vadez",
                "hash": "607c93b2cd73ba00060b137f",
                "avatar": "https://cdn.beatsaver.com/avatar/530886659240230915.png",
                "type": "DISCORD"
            },
            "metadata": {
                "bpm": 160.06,
                "duration": 406,
                "songName": "Stan",
                "songSubName": "Feat Dido",
                "songAuthorName": "Eminem",
                "levelAuthorName": "Vadez"
            },
            "stats": {
                "plays": 0,
                "downloads": 0,
                "upvotes": 126,
                "downvotes": 7,
                "score": 0.845
            },
            "uploaded": "2022-01-01T03:03:49.873706Z",
            "automapper": false,
            "ranked": false,
            "qualified": false,
            "versions": [
                {
                    "hash": "67ece9eb221fe0c5c089286b61970b4c4aeae5eb",
                    "state": "Published",
                    "createdAt": "2022-02-17T20:31:09.359844Z",
                    "sageScore": 3,
                    "diffs": [
                        {
                            "njs": 19.0,
                            "offset": -0.2,
                            "notes": 1924,
                            "bombs": 0,
                            "obstacles": 0,
                            "nps": 4.863,
                            "length": 1055.5,
                            "characteristic": "Standard",
                            "difficulty": "ExpertPlus",
                            "events": 2209,
                            "chroma": true,
                            "me": false,
                            "ne": true,
                            "cinema": false,
                            "seconds": 395.664,
                            "paritySummary": {
                                "errors": 0,
                                "warns": 0,
                                "resets": 0
                            }
                        }
                    ],
                    "downloadURL": "https://na.cdn.beatsaver.com/67ece9eb221fe0c5c089286b61970b4c4aeae5eb.zip",
                    "coverURL": "https://na.cdn.beatsaver.com/67ece9eb221fe0c5c089286b61970b4c4aeae5eb.jpg",
                    "previewURL": "https://na.cdn.beatsaver.com/67ece9eb221fe0c5c089286b61970b4c4aeae5eb.mp3"
                }
            ],
            "createdAt": "2022-01-01T03:02:53.168612Z",
            "updatedAt": "2022-02-17T20:40:57.605711Z",
            "lastPublishedAt": "2022-02-17T20:31:13.278222Z",
            "tags": [
                "hip-hop-rap",
                "balanced"
            ]
        },
        {
            "id": "21d93",
            "name": "Rihanna - Disturbia (7_7 bootleg)",
            "description": "wanna see what people can get and then maybe lowers and rank",
            "uploader": {
                "id": 4284468,
                "name": "aquaflee0",
                "hash": "5f93369db27da400077245b3",
                "avatar": "https://cdn.beatsaver.com/avatar/386558897655250947.png",
                "type": "DISCORD"
            },
            "metadata": {
                "bpm": 280.0,
                "duration": 110,
                "songName": "Disturbia",
                "songSubName": "(7_7 Bootleg)",
                "songAuthorName": "Rihanna",
                "levelAuthorName": "Aquaflee"
            },
            "stats": {
                "plays": 0,
                "downloads": 0,
                "upvotes": 10,
                "downvotes": 1,
                "score": 0.7155
            },
            "uploaded": "2022-02-17T20:05:29.239600Z",
            "automapper": false,
            "ranked": false,
            "qualified": false,
            "versions": [
                {
                    "hash": "220f61d973115a5eaf091f0c439ebdcfa12f85fa",
                    "state": "Published",
                    "createdAt": "2022-02-17T20:05:19.551605Z",
                    "sageScore": 5,
                    "diffs": [
                        {
                            "njs": 21.0,
                            "offset": 0.15,
                            "notes": 1512,
                            "bombs": 0,
                            "obstacles": 96,
                            "nps": 14.489,
                            "length": 487.0,
                            "characteristic": "Standard",
                            "difficulty": "ExpertPlus",
                            "events": 5086,
                            "chroma": false,
                            "me": false,
                            "ne": false,
                            "cinema": false,
                            "seconds": 104.357,
                            "paritySummary": {
                                "errors": 0,
                                "warns": 5,
                                "resets": 0
                            }
                        }
                    ],
                    "downloadURL": "https://na.cdn.beatsaver.com/220f61d973115a5eaf091f0c439ebdcfa12f85fa.zip",
                    "coverURL": "https://na.cdn.beatsaver.com/220f61d973115a5eaf091f0c439ebdcfa12f85fa.jpg",
                    "previewURL": "https://na.cdn.beatsaver.com/220f61d973115a5eaf091f0c439ebdcfa12f85fa.mp3"
                }
            ],
            "createdAt": "2022-02-17T20:05:19.551605Z",
            "updatedAt": "2022-02-17T20:05:29.239600Z",
            "lastPublishedAt": "2022-02-17T20:05:29.239600Z"
        },
        {
            "id": "1f705",
            "name": "Circles!",
            "description": "holy moly a collab map???????????? wowowowowoowowow\n(collab with uiop327 - https://beatsaver.com/profile/62310)\n\nlights made with lolilighter\n\nlaaazi: 0:00 - 0:34\nuiop327: 0:35 - 1:37\nlaaazi: 1:38 - end\n\ntech map??//??????????????? (no shot)\nreal\nuhhhhhhhhhh enjoy the map or something\nj",
            "uploader": {
                "id": 4283426,
                "name": "laaazi",
                "hash": "60d9459b686b9f0006a5fed9",
                "avatar": "https://cdn.beatsaver.com/avatar/4283426.jpg",
                "type": "SIMPLE"
            },
            "metadata": {
                "bpm": 184.0,
                "duration": 141,
                "songName": "Circles!",
                "songSubName": "",
                "songAuthorName": "Nekodex",
                "levelAuthorName": "laaazi & uiop327"
            },
            "stats": {
                "plays": 0,
                "downloads": 0,
                "upvotes": 10,
                "downvotes": 0,
                "score": 0.7571
            },
            "uploaded": "2021-12-30T22:31:57.868703Z",
            "automapper": false,
            "ranked": false,
            "qualified": false,
            "versions": [
                {
                    "hash": "115e5f35c83ea73d4dba0eb6f4678c6718f27ee0",
                    "state": "Published",
                    "createdAt": "2021-12-30T22:29:51.327271Z",
                    "sageScore": 1,
                    "diffs": [
                        {
                            "njs": 21.5,
                            "offset": -0.55,
                            "notes": 1261,
                            "bombs": 144,
                            "obstacles": 98,
                            "nps": 9.372,
                            "length": 412.625,
                            "characteristic": "Standard",
                            "difficulty": "ExpertPlus",
                            "events": 5689,
                            "chroma": false,
                            "me": false,
                            "ne": false,
                            "cinema": false,
                            "seconds": 134.552,
                            "paritySummary": {
                                "errors": 0,
                                "warns": 2,
                                "resets": 23
                            }
                        }
                    ],
                    "downloadURL": "https://na.cdn.beatsaver.com/115e5f35c83ea73d4dba0eb6f4678c6718f27ee0.zip",
                    "coverURL": "https://na.cdn.beatsaver.com/115e5f35c83ea73d4dba0eb6f4678c6718f27ee0.jpg",
                    "previewURL": "https://na.cdn.beatsaver.com/115e5f35c83ea73d4dba0eb6f4678c6718f27ee0.mp3"
                }
            ],
            "createdAt": "2021-12-30T22:25:19.333185Z",
            "updatedAt": "2022-02-17T19:58:36.249605Z",
            "lastPublishedAt": "2021-12-30T22:31:57.868703Z",
            "tags": [
                "balanced",
                "video-game-soundtrack"
            ]
        },
        {
            "id": "1e086",
            "name": "BANG!!! - EGOIST",
            "description": "🥶 🍨 BANG CHILLING",
            "uploader": {
                "id": 4284577,
                "name": "uninstaller",
                "hash": "5cff0b7598cc5a672c85248e",
                "avatar": "https://cdn.beatsaver.com/avatar/84840552935194624.png",
                "type": "DISCORD"
            },
            "metadata": {
                "bpm": 137.0,
                "duration": 191,
                "songName": "BANG!!!",
                "songSubName": "",
                "songAuthorName": "EGOIST",
                "levelAuthorName": "CoolingCloset & Uninstaller"
            },
            "stats": {
                "plays": 0,
                "downloads": 0,
                "upvotes": 88,
                "downvotes": 8,
                "score": 0.8115
            },
            "uploaded": "2021-11-16T19:40:55.342068Z",
            "automapper": false,
            "ranked": false,
            "qualified": false,
            "versions": [
                {
                    "hash": "ee6d53170f3e4a7705c8ff55a7e071725d3c9311",
                    "state": "Published",
                    "createdAt": "2021-11-16T19:40:47.962709Z",
                    "sageScore": 4,
                    "diffs": [
                        {
                            "njs": 18.0,
                            "offset": -0.8,
                            "notes": 1034,
                            "bombs": 0,
                            "obstacles": 71,
                            "nps": 5.552,
                            "length": 425.25,
                            "characteristic": "Standard",
                            "difficulty": "ExpertPlus",
                            "events": 3753,
                            "chroma": false,
                            "me": false,
                            "ne": false,
                            "cinema": false,
                            "seconds": 186.241,
                            "paritySummary": {
                                "errors": 0,
                                "warns": 19,
                                "resets": 0
                            }
                        },
                        {
                            "njs": 18.0,
                            "offset": -0.5,
                            "notes": 1025,
                            "bombs": 0,
                            "obstacles": 145,
                            "nps": 5.504,
                            "length": 425.25,
                            "characteristic": "Lawless",
                            "difficulty": "ExpertPlus",
                            "events": 3760,
                            "chroma": false,
                            "me": false,
                            "ne": false,
                            "cinema": false,
                            "seconds": 186.241,
                            "paritySummary": {
                                "errors": 0,
                                "warns": 17,
                                "resets": 0
                            }
                        }
                    ],
                    "downloadURL": "https://na.cdn.beatsaver.com/ee6d53170f3e4a7705c8ff55a7e071725d3c9311.zip",
                    "coverURL": "https://na.cdn.beatsaver.com/ee6d53170f3e4a7705c8ff55a7e071725d3c9311.jpg",
                    "previewURL": "https://na.cdn.beatsaver.com/ee6d53170f3e4a7705c8ff55a7e071725d3c9311.mp3"
                }
            ],
            "curator": {
                "id": 4285437,
                "name": "vasili",
                "hash": "5e0e09f31bd27f0006575c19",
                "avatar": "https://cdn.beatsaver.com/avatar/286059015425753088.png",
                "type": "DISCORD"
            },
            "curatedAt": "2022-02-17T19:53:23.510977Z",
            "createdAt": "2021-11-16T19:32:48.180240Z",
            "updatedAt": "2022-02-17T19:53:23.510977Z",
            "lastPublishedAt": "2021-11-16T19:40:55.342068Z",
            "tags": [
                "tech",
                "techno",
                "j-pop"
            ]
        },
        {
            "id": "21d8a",
            "name": "Throne",
            "description": "ZYZZ MAP TIME!",
            "uploader": {
                "id": 4301473,
                "name": "GaryVR",
                "avatar": "https://cdn.beatsaver.com/avatar/494839179994202123.png",
                "type": "DISCORD"
            },
            "metadata": {
                "bpm": 250.0,
                "duration": 168,
                "songName": "Throne",
                "songSubName": "",
                "songAuthorName": "Tevvez",
                "levelAuthorName": "GaryVR"
            },
            "stats": {
                "plays": 0,
                "downloads": 0,
                "upvotes": 0,
                "downvotes": 0,
                "score": 0.5
            },
            "uploaded": "2022-02-17T19:22:58.152752Z",
            "automapper": false,
            "ranked": false,
            "qualified": false,
            "versions": [
                {
                    "hash": "b1b452657a9aa75772377eb139280d5f9599d293",
                    "state": "Published",
                    "createdAt": "2022-02-17T19:22:24.050062Z",
                    "sageScore": 2,
                    "diffs": [
                        {
                            "njs": 26.0,
                            "offset": -0.1587731,
                            "notes": 879,
                            "bombs": 2,
                            "obstacles": 76,
                            "nps": 5.457,
                            "length": 671.201,
                            "characteristic": "Standard",
                            "difficulty": "ExpertPlus",
                            "events": 1059,
                            "chroma": false,
                            "me": false,
                            "ne": false,
                            "cinema": false,
                            "seconds": 161.088,
                            "paritySummary": {
                                "errors": 0,
                                "warns": 0,
                                "resets": 0
                            }
                        }
                    ],
                    "downloadURL": "https://na.cdn.beatsaver.com/b1b452657a9aa75772377eb139280d5f9599d293.zip",
                    "coverURL": "https://na.cdn.beatsaver.com/b1b452657a9aa75772377eb139280d5f9599d293.jpg",
                    "previewURL": "https://na.cdn.beatsaver.com/b1b452657a9aa75772377eb139280d5f9599d293.mp3"
                }
            ],
            "createdAt": "2022-02-17T19:22:24.050062Z",
            "updatedAt": "2022-02-17T19:22:58.152752Z",
            "lastPublishedAt": "2022-02-17T19:22:58.152752Z",
            "tags": [
                "balanced",
                "drum-and-bass",
                "dubstep",
                "tech"
            ]
        },
        {
            "id": "21d48",
            "name": "Vylet Pony - Little Dreams [Chroma Plus]",
            "description": "Limerence Environment (Monstercat)\n===========================\nThis map was only made to add a nostalgic feel to another map I made. Though it's nice to revisit and light in this environment again. I tried to map things as if it was late 2018.\n===========================\nBuy the song here, or visit:\nhttps://vyletpony.bandcamp.com/\nhttps://www.youtube.com/user/MusiciansOfPonyville\nhttp://www.vyletpony.com",
            "uploader": {
                "id": 2885,
                "name": "zyx_xd",
                "hash": "5e8fdc383f476a00064ff50c",
                "avatar": "https://www.gravatar.com/avatar/5e8fdc383f476a00064ff50c?d=retro",
                "type": "SIMPLE"
            },
            "metadata": {
                "bpm": 130.0,
                "duration": 310,
                "songName": "Little Dreams",
                "songSubName": "",
                "songAuthorName": "Vylet Pony",
                "levelAuthorName": "Zyxi"
            },
            "stats": {
                "plays": 0,
                "downloads": 0,
                "upvotes": 11,
                "downvotes": 0,
                "score": 0.7634
            },
            "uploaded": "2022-02-17T11:57:34.418588Z",
            "automapper": false,
            "ranked": false,
            "qualified": false,
            "versions": [
                {
                    "hash": "4ad02610f0e7663b932cae3c1973030b6392d67b",
                    "state": "Published",
                    "createdAt": "2022-02-17T19:01:00.776415Z",
                    "sageScore": 4,
                    "diffs": [
                        {
                            "njs": 20.0,
                            "offset": 0.25,
                            "notes": 1520,
                            "bombs": 0,
                            "obstacles": 0,
                            "nps": 5.203,
                            "length": 633.0,
                            "characteristic": "Standard",
                            "difficulty": "ExpertPlus",
                            "events": 8790,
                            "chroma": true,
                            "me": false,
                            "ne": false,
                            "cinema": false,
                            "seconds": 292.154,
                            "paritySummary": {
                                "errors": 0,
                                "warns": 0,
                                "resets": 0
                            }
                        }
                    ],
                    "downloadURL": "https://na.cdn.beatsaver.com/4ad02610f0e7663b932cae3c1973030b6392d67b.zip",
                    "coverURL": "https://na.cdn.beatsaver.com/4ad02610f0e7663b932cae3c1973030b6392d67b.jpg",
                    "previewURL": "https://na.cdn.beatsaver.com/4ad02610f0e7663b932cae3c1973030b6392d67b.mp3"
                }
            ],
            "createdAt": "2022-02-17T11:50:15.480795Z",
            "updatedAt": "2022-02-17T19:01:17.804076Z",
            "lastPublishedAt": "2022-02-17T19:01:17.804076Z",
            "tags": [
                "dance-style",
                "balanced",
                "electronic",
                "alternative"
            ]
        },
        {
            "id": "21d75",
            "name": "Itou Kanako - Technovision (Short ver.)",
            "description": "(from Steins;Gate OST)\r\n\r\nFirst map. I purposely used the short version of this song to motivate myself to put out something complete, but if I end up making more maps, I'll try to come back to this one and map the full version of the song.\r\n\r\nBig thanks to monstor and SputNix for playtesting and giving valuable feedback. Hope it plays well even though it's my first map.\r\n\r\nEnjoy.\r\n(El. Psy. Kongroo.)\r\n(Yes I had to.)\r\n",
            "uploader": {
                "id": 4323025,
                "name": "Lugunium",
                "avatar": "https://cdn.beatsaver.com/avatar/176918070885875713.png",
                "type": "DISCORD"
            },
            "metadata": {
                "bpm": 145.0,
                "duration": 97,
                "songName": "Technovision",
                "songSubName": "(Short Ver.)",
                "songAuthorName": "Itou Kanako",
                "levelAuthorName": "Lugunium"
            },
            "stats": {
                "plays": 0,
                "downloads": 0,
                "upvotes": 4,
                "downvotes": 1,
                "score": 0.6251
            },
            "uploaded": "2022-02-17T18:36:26.552652Z",
            "automapper": false,
            "ranked": false,
            "qualified": false,
            "versions": [
                {
                    "hash": "0a7770017d5975477bf4f22a6b19a32040bb2143",
                    "state": "Published",
                    "createdAt": "2022-02-17T18:35:30.228202Z",
                    "sageScore": 4,
                    "diffs": [
                        {
                            "njs": 16.0,
                            "offset": -0.1,
                            "notes": 415,
                            "bombs": 0,
                            "obstacles": 25,
                            "nps": 4.477,
                            "length": 224.0,
                            "characteristic": "Standard",
                            "difficulty": "Expert",
                            "events": 1191,
                            "chroma": false,
                            "me": false,
                            "ne": false,
                            "cinema": false,
                            "seconds": 92.69,
                            "paritySummary": {
                                "errors": 0,
                                "warns": 0,
                                "resets": 0
                            }
                        }
                    ],
                    "downloadURL": "https://na.cdn.beatsaver.com/0a7770017d5975477bf4f22a6b19a32040bb2143.zip",
                    "coverURL": "https://na.cdn.beatsaver.com/0a7770017d5975477bf4f22a6b19a32040bb2143.jpg",
                    "previewURL": "https://na.cdn.beatsaver.com/0a7770017d5975477bf4f22a6b19a32040bb2143.mp3"
                }
            ],
            "createdAt": "2022-02-17T18:35:30.228202Z",
            "updatedAt": "2022-02-17T18:36:26.552652Z",
            "lastPublishedAt": "2022-02-17T18:36:26.552652Z"
        },
        {
            "id": "1fa21",
            "name": "[Queue] uma - Chakra",
            "description": "ethnic puzzle mapping\ndance tech map wow!!\nfor rank at some point i just need another dif and foxy might make a dif\n\nthanks dash for the modnmfn f\nthanks bitz for da qatbhujkejg\nits a full spread now!\n\nStar Estimate - 10.4",
            "uploader": {
                "id": 4287112,
                "name": "jabob",
                "hash": "5ee92cb978d61a00065b345b",
                "avatar": "https://cdn.beatsaver.com/avatar/195639236672618496.png",
                "type": "DISCORD"
            },
            "metadata": {
                "bpm": 165.0,
                "duration": 122,
                "songName": "Chakra",
                "songSubName": "",
                "songAuthorName": "uma",
                "levelAuthorName": "Jabob"
            },
            "stats": {
                "plays": 0,
                "downloads": 0,
                "upvotes": 83,
                "downvotes": 11,
                "score": 0.7857
            },
            "uploaded": "2022-01-04T01:05:23.962633Z",
            "automapper": false,
            "ranked": false,
            "qualified": false,
            "versions": [
                {
                    "hash": "8e6bc0438a81c60aeec4e9afb937145fc9ecd947",
                    "state": "Published",
                    "createdAt": "2022-02-17T18:32:52.192437Z",
                    "sageScore": 8,
                    "diffs": [
                        {
                            "njs": 13.0,
                            "offset": 0.65,
                            "notes": 346,
                            "bombs": 0,
                            "obstacles": 199,
                            "nps": 2.973,
                            "length": 320.0,
                            "characteristic": "Standard",
                            "difficulty": "Easy",
                            "events": 3915,
                            "chroma": false,
                            "me": false,
                            "ne": false,
                            "cinema": false,
                            "seconds": 116.364,
                            "paritySummary": {
                                "errors": 0,
                                "warns": 0,
                                "resets": 0
                            }
                        },
                        {
                            "njs": 15.0,
                            "offset": 0.15,
                            "notes": 459,
                            "bombs": 0,
                            "obstacles": 200,
                            "nps": 3.945,
                            "length": 320.0,
                            "characteristic": "Standard",
                            "difficulty": "Normal",
                            "events": 3915,
                            "chroma": false,
                            "me": false,
                            "ne": false,
                            "cinema": false,
                            "seconds": 116.364,
                            "paritySummary": {
                                "errors": 0,
                                "warns": 0,
                                "resets": 0
                            }
                        },
                        {
                            "njs": 17.0,
                            "offset": -0.3,
                            "notes": 634,
                            "bombs": 15,
                            "obstacles": 193,
                            "nps": 5.448,
                            "length": 320.0,
                            "characteristic": "Standard",
                            "difficulty": "Hard",
                            "events": 3915,
                            "chroma": false,
                            "me": false,
                            "ne": false,
                            "cinema": false,
                            "seconds": 116.364,
                            "paritySummary": {
                                "errors": 0,
                                "warns": 0,
                                "resets": 6
                            }
                        },
                        {
                            "njs": 18.5,
                            "offset": -0.55,
                            "notes": 792,
                            "bombs": 29,
                            "obstacles": 181,
                            "nps": 6.806,
                            "length": 320.0,
                            "characteristic": "Standard",
                            "difficulty": "Expert",
                            "events": 3915,
                            "chroma": false,
                            "me": false,
                            "ne": false,
                            "cinema": false,
                            "seconds": 116.364,
                            "paritySummary": {
                                "errors": 0,
                                "warns": 8,
                                "resets": 8
                            }
                        },
                        {
                            "njs": 19.0,
                            "offset": -0.7,
                            "notes": 931,
                            "bombs": 79,
                            "obstacles": 181,
                            "nps": 8.001,
                            "length": 320.0,
                            "characteristic": "Standard",
                            "difficulty": "ExpertPlus",
                            "events": 3929,
                            "chroma": false,
                            "me": false,
                            "ne": false,
                            "cinema": false,
                            "seconds": 116.364,
                            "paritySummary": {
                                "errors": 3,
                                "warns": 58,
                                "resets": 9
                            }
                        }
                    ],
                    "downloadURL": "https://na.cdn.beatsaver.com/8e6bc0438a81c60aeec4e9afb937145fc9ecd947.zip",
                    "coverURL": "https://na.cdn.beatsaver.com/8e6bc0438a81c60aeec4e9afb937145fc9ecd947.jpg",
                    "previewURL": "https://na.cdn.beatsaver.com/8e6bc0438a81c60aeec4e9afb937145fc9ecd947.mp3"
                }
            ],
            "createdAt": "2022-01-04T01:05:12.758316Z",
            "updatedAt": "2022-02-17T18:33:13.592042Z",
            "lastPublishedAt": "2022-02-17T18:32:56.098515Z",
            "tags": [
                "tech",
                "dance-style",
                "electronic"
            ]
        },
        {
            "id": "21d67",
            "name": "GANGSTERS PARADISE",
            "description": "REUPLOAD TO FIX SMALL DETAILS MY BAD\n\nSTILL FIRST MAP\nKINDA OK THO",
            "uploader": {
                "id": 4322876,
                "name": "Nebroka",
                "avatar": "https://cdn.beatsaver.com/avatar/4322876.jpg",
                "type": "SIMPLE"
            },
            "metadata": {
                "bpm": 200.0,
                "duration": 247,
                "songName": "GANGSTERS PARADISE",
                "songSubName": "",
                "songAuthorName": "Envy",
                "levelAuthorName": "Nebroka"
            },
            "stats": {
                "plays": 0,
                "downloads": 0,
                "upvotes": 6,
                "downvotes": 4,
                "score": 0.5514
            },
            "uploaded": "2022-02-17T18:12:07.818354Z",
            "automapper": false,
            "ranked": false,
            "qualified": false,
            "versions": [
                {
                    "hash": "dff7c7e1398e20d89fd6f0751774985d35b4da34",
                    "state": "Published",
                    "createdAt": "2022-02-17T18:18:20.599971Z",
                    "sageScore": 3,
                    "diffs": [
                        {
                            "njs": 19.0,
                            "offset": 0.0,
                            "notes": 1453,
                            "bombs": 0,
                            "obstacles": 48,
                            "nps": 6.565,
                            "length": 737.75,
                            "characteristic": "Standard",
                            "difficulty": "ExpertPlus",
                            "events": 5490,
                            "chroma": false,
                            "me": false,
                            "ne": false,
                            "cinema": false,
                            "seconds": 221.325,
                            "paritySummary": {
                                "errors": 12,
                                "warns": 3,
                                "resets": 0
                            }
                        }
                    ],
                    "downloadURL": "https://na.cdn.beatsaver.com/dff7c7e1398e20d89fd6f0751774985d35b4da34.zip",
                    "coverURL": "https://na.cdn.beatsaver.com/dff7c7e1398e20d89fd6f0751774985d35b4da34.jpg",
                    "previewURL": "https://na.cdn.beatsaver.com/dff7c7e1398e20d89fd6f0751774985d35b4da34.mp3"
                }
            ],
            "createdAt": "2022-02-17T18:11:28.615007Z",
            "updatedAt": "2022-02-17T18:22:37.107362Z",
            "lastPublishedAt": "2022-02-17T18:18:32.421500Z",
            "tags": [
                "speed",
                "speedcore",
                "hardcore",
                "challenge"
            ]
        }
    ]
}