{"_version":"1.5.0","_beatsPerMinute":98,"_beatsPerBar":16,"_noteJumpSpeed":10,"_shuffle":0,"_shufflePeriod":0.5,"_events":[{"_time":1.8774999380111694,"_type":4,"_value":5},{"_time":1.8774999380111694,"_type":1,"_value":5},{"_time":2.877500057220459,"_type":1,"_value":7},{"_time":4.877500057220459,"_type":0,"_value":7},{"_time":4.877500057220459,"_type":1,"_value":5},{"_time":5.127500057220459,"_type":1,"_value":7},{"_time":5.877500057220459,"_type":1,"_value":1},{"_time":5.877500057220459,"_type":4,"_value":1},{"_time":6.877500057220459,"_type":1,"_value":3},{"_time":8.8774995803833008,"_type":1,"_value":1},{"_time":8.8774995803833008,"_type":0,"_value":3},{"_time":9.1274995803833008,"_type":1,"_value":3},{"_time":9.8774995803833008,"_type":1,"_value":5},{"_time":9.8774995803833008,"_type":4,"_value":5},{"_time":10.877499580383301,"_type":1,"_value":7},{"_time":12.877499580383301,"_type":0,"_value":7},{"_time":12.877499580383301,"_type":1,"_value":5},{"_time":13.127499580383301,"_type":1,"_value":7},{"_time":13.877499580383301,"_type":1,"_value":1},{"_time":13.877499580383301,"_type":4,"_value":1},{"_time":14.877499580383301,"_type":1,"_value":3}],"_notes":[{"_time":1.8774999380111694,"_lineIndex":3,"_lineLayer":1,"_type":1,"_cutDirection":3},{"_time":1.8774999380111694,"_lineIndex":0,"_lineLayer":1,"_type":0,"_cutDirection":2},{"_time":4.877500057220459,"_lineIndex":0,"_lineLayer":1,"_type":0,"_cutDirection":3},{"_time":4.877500057220459,"_lineIndex":3,"_lineLayer":1,"_type":1,"_cutDirection":2},{"_time":5.877500057220459,"_lineIndex":2,"_lineLayer":0,"_type":1,"_cutDirection":1},{"_time":5.877500057220459,"_lineIndex":1,"_lineLayer":0,"_type":0,"_cutDirection":1},{"_time":8.8774995803833008,"_lineIndex":2,"_lineLayer":0,"_type":1,"_cutDirection":0},{"_time":8.8774995803833008,"_lineIndex":1,"_lineLayer":0,"_type":0,"_cutDirection":0},{"_time":9.8774995803833008,"_lineIndex":3,"_lineLayer":0,"_type":1,"_cutDirection":7},{"_time":9.8774995803833008,"_lineIndex":0,"_lineLayer":0,"_type":0,"_cutDirection":6},{"_time":12.877499580383301,"_lineIndex":3,"_lineLayer":0,"_type":1,"_cutDirection":4},{"_time":12.877499580383301,"_lineIndex":0,"_lineLayer":0,"_type":0,"_cutDirection":5},{"_time":13.877499580383301,"_lineIndex":0,"_lineLayer":1,"_type":0,"_cutDirection":2},{"_time":13.877499580383301,"_lineIndex":3,"_lineLayer":1,"_type":1,"_cutDirection":3},{"_time":15.877499580383301,"_lineIndex":0,"_lineLayer":1,"_type":0,"_cutDirection":8},{"_time":15.877499580383301,"_lineIndex":3,"_lineLayer":0,"_type":1,"_cutDirection":1},{"_time":16.377500534057617,"_lineIndex":0,"_lineLayer":1,"_type":0,"_cutDirection":8},{"_time":16.877500534057617,"_lineIndex":3,"_lineLayer":0,"_type":1,"_cutDirection":0},{"_time":16.877500534057617,"_lineIndex":0,"_lineLayer":1,"_type":0,"_cutDirection":8},{"_time":17.127500534057617,"_lineIndex":0,"_lineLayer":1,"_type":0,"_cutDirection":8},{"_time":17.877500534057617,"_lineIndex":3,"_lineLayer":0,"_type":1,"_cutDirection":1},{"_time":18.877500534057617,"_lineIndex":0,"_lineLayer":2,"_type":0,"_cutDirection":4},{"_time":20.877500534057617,"_lineIndex":0,"_lineLayer":2,"_type":0,"_cutDirection":4},{"_time":21.877500534057617,"_lineIndex":2,"_lineLayer":0,"_type":1,"_cutDirection":1},{"_time":21.877500534057617,"_lineIndex":1,"_lineLayer":0,"_type":0,"_cutDirection":1},{"_time":22.877500534057617,"_lineIndex":0,"_lineLayer":2,"_type":0,"_cutDirection":4},{"_time":24.877500534057617,"_lineIndex":0,"_lineLayer":2,"_type":0,"_cutDirection":4},{"_time":25.877500534057617,"_lineIndex":2,"_lineLayer":0,"_type":1,"_cutDirection":1},{"_time":25.877500534057617,"_lineIndex":1,"_lineLayer":0,"_type":0,"_cutDirection":1},{"_time":26.877500534057617,"_lineIndex":3,"_lineLayer":2,"_type":1,"_cutDirection":5},{"_time":28.877500534057617,"_lineIndex":3,"_lineLayer":2,"_type":1,"_cutDirection":5},{"_time":29.877500534057617,"_lineIndex":2,"_lineLayer":0,"_type":1,"_cutDirection":1},{"_time":29.877500534057617,"_lineIndex":1,"_lineLayer":0,"_type":0,"_cutDirection":1},{"_time":30.877500534057617,"_lineIndex":3,"_lineLayer":2,"_type":1,"_cutDirection":5},{"_time":32.877498626708984,"_lineIndex":3,"_lineLayer":2,"_type":1,"_cutDirection":5},{"_time":33.877498626708984,"_lineIndex":2,"_lineLayer":0,"_type":1,"_cutDirection":1},{"_time":33.877498626708984,"_lineIndex":1,"_lineLayer":0,"_type":0,"_cutDirection":1},{"_time":34.502498626708984,"_lineIndex":1,"_lineLayer":0,"_type":0,"_cutDirection":0},{"_time":34.502498626708984,"_lineIndex":2,"_lineLayer":0,"_type":1,"_cutDirection":0},{"_time":35.377498626708984,"_lineIndex":1,"_lineLayer":0,"_type":0,"_cutDirection":1},{"_time":35.377498626708984,"_lineIndex":2,"_lineLayer":0,"_type":1,"_cutDirection":1},{"_time":36.377498626708984,"_lineIndex":2,"_lineLayer":0,"_type":1,"_cutDirection":0},{"_time":36.377498626708984,"_lineIndex":1,"_lineLayer":0,"_type":0,"_cutDirection":0},{"_time":36.877498626708984,"_lineIndex":3,"_lineLayer":2,"_type":1,"_cutDirection":5},{"_time":37.877498626708984,"_lineIndex":1,"_lineLayer":0,"_type":0,"_cutDirection":1},{"_time":37.877498626708984,"_lineIndex":2,"_lineLayer":0,"_type":1,"_cutDirection":1},{"_time":38.502498626708984,"_lineIndex":1,"_lineLayer":0,"_type":0,"_cutDirection":0},{"_time":38.502498626708984,"_lineIndex":2,"_lineLayer":0,"_type":1,"_cutDirection":0},{"_time":39.377498626708984,"_lineIndex":1,"_lineLayer":0,"_type":0,"_cutDirection":1},{"_time":39.377498626708984,"_lineIndex":2,"_lineLayer":0,"_type":1,"_cutDirection":1},{"_time":40.377498626708984,"_lineIndex":2,"_lineLayer":0,"_type":1,"_cutDirection":0},{"_time":40.377498626708984,"_lineIndex":1,"_lineLayer":0,"_type":0,"_cutDirection":0},{"_time":40.877498626708984,"_lineIndex":0,"_lineLayer":1,"_type":0,"_cutDirection":8},{"_time":41.127498626708984,"_lineIndex":0,"_lineLayer":1,"_type":0,"_cutDirection":8},{"_time":41.377498626708984,"_lineIndex":0,"_lineLayer":1,"_type":0,"_cutDirection":8},{"_time":41.877498626708984,"_lineIndex":0,"_lineLayer":0,"_type":0,"_cutDirection":1},{"_time":41.877498626708984,"_lineIndex":1,"_lineLayer":0,"_type":1,"_cutDirection":1},{"_time":42.502498626708984,"_lineIndex":1,"_lineLayer":0,"_type":1,"_cutDirection":0},{"_time":42.502498626708984,"_lineIndex":0,"_lineLayer":0,"_type":0,"_cutDirection":0},{"_time":43.377498626708984,"_lineIndex":1,"_lineLayer":0,"_type":1,"_cutDirection":1},{"_time":43.377498626708984,"_lineIndex":0,"_lineLayer":0,"_type":0,"_cutDirection":1},{"_time":44.377498626708984,"_lineIndex":0,"_lineLayer":0,"_type":0,"_cutDirection":0},{"_time":44.377498626708984,"_lineIndex":1,"_lineLayer":0,"_type":1,"_cutDirection":0},{"_time":44.877498626708984,"_lineIndex":2,"_lineLayer":2,"_type":1,"_cutDirection":5},{"_time":45.877498626708984,"_lineIndex":1,"_lineLayer":0,"_type":1,"_cutDirection":1},{"_time":45.877498626708984,"_lineIndex":0,"_lineLayer":0,"_type":0,"_cutDirection":1},{"_time":46.502498626708984,"_lineIndex":0,"_lineLayer":0,"_type":0,"_cutDirection":0},{"_time":46.502498626708984,"_lineIndex":1,"_lineLayer":0,"_type":1,"_cutDirection":0},{"_time":47.377498626708984,"_lineIndex":1,"_lineLayer":0,"_type":1,"_cutDirection":1},{"_time":47.377498626708984,"_lineIndex":0,"_lineLayer":0,"_type":0,"_cutDirection":1},{"_time":48.377498626708984,"_lineIndex":0,"_lineLayer":0,"_type":0,"_cutDirection":0},{"_time":48.377498626708984,"_lineIndex":1,"_lineLayer":0,"_type":1,"_cutDirection":0},{"_time":48.877498626708984,"_lineIndex":0,"_lineLayer":2,"_type":0,"_cutDirection":0},{"_time":49.377498626708984,"_lineIndex":0,"_lineLayer":2,"_type":0,"_cutDirection":1},{"_time":49.877498626708984,"_lineIndex":2,"_lineLayer":0,"_type":0,"_cutDirection":1},{"_time":49.877498626708984,"_lineIndex":3,"_lineLayer":0,"_type":1,"_cutDirection":1},{"_time":50.502498626708984,"_lineIndex":2,"_lineLayer":0,"_type":0,"_cutDirection":0},{"_time":50.502498626708984,"_lineIndex":3,"_lineLayer":0,"_type":1,"_cutDirection":0},{"_time":51.377498626708984,"_lineIndex":3,"_lineLayer":0,"_type":1,"_cutDirection":1},{"_time":51.377498626708984,"_lineIndex":2,"_lineLayer":0,"_type":0,"_cutDirection":1},{"_time":52.377498626708984,"_lineIndex":3,"_lineLayer":0,"_type":1,"_cutDirection":0},{"_time":52.377498626708984,"_lineIndex":2,"_lineLayer":0,"_type":0,"_cutDirection":0},{"_time":52.877498626708984,"_lineIndex":1,"_lineLayer":2,"_type":0,"_cutDirection":4},{"_time":53.377498626708984,"_lineIndex":1,"_lineLayer":2,"_type":0,"_cutDirection":7},{"_time":53.877498626708984,"_lineIndex":2,"_lineLayer":0,"_type":0,"_cutDirection":1},{"_time":53.877498626708984,"_lineIndex":3,"_lineLayer":0,"_type":1,"_cutDirection":1},{"_time":54.502498626708984,"_lineIndex":3,"_lineLayer":0,"_type":1,"_cutDirection":0},{"_time":54.502498626708984,"_lineIndex":2,"_lineLayer":0,"_type":0,"_cutDirection":0},{"_time":55.377498626708984,"_lineIndex":2,"_lineLayer":0,"_type":0,"_cutDirection":1},{"_time":55.377498626708984,"_lineIndex":3,"_lineLayer":0,"_type":1,"_cutDirection":1},{"_time":56.377498626708984,"_lineIndex":2,"_lineLayer":0,"_type":0,"_cutDirection":0},{"_time":56.377498626708984,"_lineIndex":3,"_lineLayer":0,"_type":1,"_cutDirection":0},{"_time":56.877498626708984,"_lineIndex":3,"_lineLayer":1,"_type":1,"_cutDirection":8},{"_time":57.127498626708984,"_lineIndex":3,"_lineLayer":1,"_type":1,"_cutDirection":8},{"_time":57.377498626708984,"_lineIndex":3,"_lineLayer":1,"_type":1,"_cutDirection":8},{"_time":57.877498626708984,"_lineIndex":2,"_lineLayer":0,"_type":1,"_cutDirection":1},{"_time":57.877498626708984,"_lineIndex":1,"_lineLayer":0,"_type":0,"_cutDirection":1},{"_time":58.502498626708984,"_lineIndex":1,"_lineLayer":0,"_type":0,"_cutDirection":0},{"_time":58.502498626708984,"_lineIndex":2,"_lineLayer":0,"_type":1,"_cutDirection":0},{"_time":59.377498626708984,"_lineIndex":2,"_lineLayer":0,"_type":1,"_cutDirection":1},{"_time":59.377498626708984,"_lineIndex":1,"_lineLayer":0,"_type":0,"_cutDirection":1},{"_time":60.377498626708984,"_lineIndex":2,"_lineLayer":0,"_type":1,"_cutDirection":0},{"_time":60.377498626708984,"_lineIndex":1,"_lineLayer":0,"_type":0,"_cutDirection":0},{"_time":60.877498626708984,"_lineIndex":0,"_lineLayer":2,"_type":0,"_cutDirection":4},{"_time":61.877498626708984,"_lineIndex":1,"_lineLayer":0,"_type":0,"_cutDirection":1},{"_time":61.877498626708984,"_lineIndex":2,"_lineLayer":0,"_type":1,"_cutDirection":1},{"_time":62.502498626708984,"_lineIndex":2,"_lineLayer":0,"_type":1,"_cutDirection":0},{"_time":62.502498626708984,"_lineIndex":1,"_lineLayer":0,"_type":0,"_cutDirection":0},{"_time":63.377498626708984,"_lineIndex":1,"_lineLayer":0,"_type":0,"_cutDirection":1},{"_time":63.377498626708984,"_lineIndex":2,"_lineLayer":0,"_type":1,"_cutDirection":1},{"_time":64.37750244140625,"_lineIndex":2,"_lineLayer":0,"_type":1,"_cutDirection":0},{"_time":64.37750244140625,"_lineIndex":1,"_lineLayer":0,"_type":0,"_cutDirection":0},{"_time":64.87750244140625,"_lineIndex":3,"_lineLayer":2,"_type":1,"_cutDirection":8},{"_time":65.12750244140625,"_lineIndex":3,"_lineLayer":2,"_type":1,"_cutDirection":8},{"_time":65.37750244140625,"_lineIndex":3,"_lineLayer":2,"_type":1,"_cutDirection":8},{"_time":65.87750244140625,"_lineIndex":2,"_lineLayer":0,"_type":1,"_cutDirection":1},{"_time":66.87750244140625,"_lineIndex":2,"_lineLayer":0,"_type":1,"_cutDirection":0},{"_time":67.87750244140625,"_lineIndex":1,"_lineLayer":0,"_type":0,"_cutDirection":1},{"_time":68.87750244140625,"_lineIndex":1,"_lineLayer":0,"_type":0,"_cutDirection":0},{"_time":69.37750244140625,"_lineIndex":1,"_lineLayer":0,"_type":0,"_cutDirection":1},{"_time":69.87750244140625,"_lineIndex":1,"_lineLayer":0,"_type":0,"_cutDirection":0},{"_time":70.87750244140625,"_lineIndex":2,"_lineLayer":0,"_type":1,"_cutDirection":1},{"_time":71.87750244140625,"_lineIndex":2,"_lineLayer":0,"_type":1,"_cutDirection":0},{"_time":72.87750244140625,"_lineIndex":2,"_lineLayer":0,"_type":1,"_cutDirection":8},{"_time":73.12750244140625,"_lineIndex":2,"_lineLayer":0,"_type":1,"_cutDirection":8},{"_time":73.87750244140625,"_lineIndex":0,"_lineLayer":0,"_type":0,"_cutDirection":1},{"_time":74.87750244140625,"_lineIndex":0,"_lineLayer":0,"_type":0,"_cutDirection":0},{"_time":75.87750244140625,"_lineIndex":0,"_lineLayer":0,"_type":0,"_cutDirection":1},{"_time":76.87750244140625,"_lineIndex":0,"_lineLayer":0,"_type":0,"_cutDirection":0},{"_time":77.37750244140625,"_lineIndex":0,"_lineLayer":0,"_type":0,"_cutDirection":1},{"_time":77.87750244140625,"_lineIndex":0,"_lineLayer":0,"_type":0,"_cutDirection":0},{"_time":78.87750244140625,"_lineIndex":2,"_lineLayer":0,"_type":1,"_cutDirection":1},{"_time":79.87750244140625,"_lineIndex":3,"_lineLayer":0,"_type":1,"_cutDirection":0},{"_time":80.87750244140625,"_lineIndex":3,"_lineLayer":0,"_type":1,"_cutDirection":8},{"_time":81.12750244140625,"_lineIndex":3,"_lineLayer":0,"_type":1,"_cutDirection":8},{"_time":81.87750244140625,"_lineIndex":2,"_lineLayer":0,"_type":0,"_cutDirection":1},{"_time":81.87750244140625,"_lineIndex":3,"_lineLayer":0,"_type":1,"_cutDirection":1},{"_time":82.87750244140625,"_lineIndex":1,"_lineLayer":0,"_type":0,"_cutDirection":0},{"_time":82.87750244140625,"_lineIndex":2,"_lineLayer":0,"_type":1,"_cutDirection":0},{"_time":83.87750244140625,"_lineIndex":2,"_lineLayer":0,"_type":1,"_cutDirection":1},{"_time":83.87750244140625,"_lineIndex":1,"_lineLayer":0,"_type":0,"_cutDirection":1},{"_time":84.87750244140625,"_lineIndex":2,"_lineLayer":0,"_type":1,"_cutDirection":0},{"_time":84.87750244140625,"_lineIndex":1,"_lineLayer":0,"_type":0,"_cutDirection":0},{"_time":85.87750244140625,"_lineIndex":0,"_lineLayer":0,"_type":0,"_cutDirection":1},{"_time":85.87750244140625,"_lineIndex":3,"_lineLayer":0,"_type":1,"_cutDirection":1},{"_time":86.87750244140625,"_lineIndex":0,"_lineLayer":0,"_type":0,"_cutDirection":0},{"_time":86.87750244140625,"_lineIndex":3,"_lineLayer":0,"_type":1,"_cutDirection":0},{"_time":87.87750244140625,"_lineIndex":1,"_lineLayer":0,"_type":1,"_cutDirection":1},{"_time":87.87750244140625,"_lineIndex":2,"_lineLayer":0,"_type":0,"_cutDirection":1},{"_time":88.87750244140625,"_lineIndex":1,"_lineLayer":0,"_type":1,"_cutDirection":0},{"_time":88.87750244140625,"_lineIndex":2,"_lineLayer":0,"_type":0,"_cutDirection":0},{"_time":89.87750244140625,"_lineIndex":0,"_lineLayer":1,"_type":0,"_cutDirection":2},{"_time":89.87750244140625,"_lineIndex":3,"_lineLayer":1,"_type":1,"_cutDirection":3},{"_time":90.87750244140625,"_lineIndex":3,"_lineLayer":1,"_type":1,"_cutDirection":2},{"_time":90.87750244140625,"_lineIndex":0,"_lineLayer":1,"_type":0,"_cutDirection":3},{"_time":91.87750244140625,"_lineIndex":0,"_lineLayer":0,"_type":0,"_cutDirection":6},{"_time":91.87750244140625,"_lineIndex":3,"_lineLayer":0,"_type":1,"_cutDirection":7},{"_time":92.87750244140625,"_lineIndex":3,"_lineLayer":0,"_type":1,"_cutDirection":4},{"_time":92.87750244140625,"_lineIndex":0,"_lineLayer":0,"_type":0,"_cutDirection":5},{"_time":93.87750244140625,"_lineIndex":1,"_lineLayer":0,"_type":0,"_cutDirection":1},{"_time":93.87750244140625,"_lineIndex":2,"_lineLayer":0,"_type":1,"_cutDirection":1},{"_time":94.87750244140625,"_lineIndex":2,"_lineLayer":0,"_type":1,"_cutDirection":0},{"_time":94.87750244140625,"_lineIndex":1,"_lineLayer":0,"_type":0,"_cutDirection":0},{"_time":95.87750244140625,"_lineIndex":2,"_lineLayer":0,"_type":1,"_cutDirection":1},{"_time":96.37750244140625,"_lineIndex":2,"_lineLayer":0,"_type":1,"_cutDirection":0},{"_time":96.87750244140625,"_lineIndex":2,"_lineLayer":0,"_type":1,"_cutDirection":1},{"_time":96.87750244140625,"_lineIndex":1,"_lineLayer":0,"_type":0,"_cutDirection":8},{"_time":97.12750244140625,"_lineIndex":1,"_lineLayer":0,"_type":0,"_cutDirection":8},{"_time":97.37750244140625,"_lineIndex":1,"_lineLayer":0,"_type":0,"_cutDirection":8},{"_time":97.62750244140625,"_lineIndex":1,"_lineLayer":0,"_type":0,"_cutDirection":8},{"_time":98.87750244140625,"_lineIndex":3,"_lineLayer":2,"_type":1,"_cutDirection":5},{"_time":100.87750244140625,"_lineIndex":0,"_lineLayer":2,"_type":0,"_cutDirection":4},{"_time":102.87750244140625,"_lineIndex":3,"_lineLayer":2,"_type":1,"_cutDirection":5},{"_time":104.87750244140625,"_lineIndex":0,"_lineLayer":2,"_type":0,"_cutDirection":4},{"_time":106.87750244140625,"_lineIndex":3,"_lineLayer":1,"_type":1,"_cutDirection":3},{"_time":108.87750244140625,"_lineIndex":0,"_lineLayer":1,"_type":0,"_cutDirection":2},{"_time":110.87750244140625,"_lineIndex":3,"_lineLayer":0,"_type":1,"_cutDirection":7},{"_time":112.87750244140625,"_lineIndex":0,"_lineLayer":0,"_type":0,"_cutDirection":6},{"_time":114.87750244140625,"_lineIndex":3,"_lineLayer":2,"_type":1,"_cutDirection":5},{"_time":116.87750244140625,"_lineIndex":0,"_lineLayer":2,"_type":0,"_cutDirection":4},{"_time":118.87750244140625,"_lineIndex":3,"_lineLayer":1,"_type":1,"_cutDirection":3},{"_time":120.87750244140625,"_lineIndex":0,"_lineLayer":1,"_type":0,"_cutDirection":2},{"_time":122.87750244140625,"_lineIndex":3,"_lineLayer":0,"_type":1,"_cutDirection":7},{"_time":124.87750244140625,"_lineIndex":0,"_lineLayer":0,"_type":0,"_cutDirection":6},{"_time":126.87750244140625,"_lineIndex":3,"_lineLayer":1,"_type":1,"_cutDirection":3},{"_time":128.87750244140625,"_lineIndex":0,"_lineLayer":1,"_type":0,"_cutDirection":2}],"_obstacles":[{"_time":73.87750244140625,"_lineIndex":2,"_type":0,"_duration":4,"_width":2},{"_time":79.87750244140625,"_lineIndex":0,"_type":0,"_duration":2,"_width":2}]}